{"info":{"file":"app/scripts/controllers/main.js","fileShort":"controllers/main.js","fileSafe":"controllers_main_js","link":"files/controllers_main_js/index.html"},"complexity":{"aggregate":{"sloc":{"logical":316,"physical":459},"cyclomatic":48,"halstead":{"operators":{"distinct":20,"total":1179,"identifiers":["__stripped__"]},"operands":{"distinct":293,"total":1406,"identifiers":["__stripped__"]},"length":2585,"vocabulary":313,"difficulty":47.98634812286689,"volume":21429.69871932082,"effort":1028332.9829134836,"bugs":7.143232906440273,"time":57129.610161860204},"params":50,"line":1,"cyclomaticDensity":15.18987341772152,"complexity":{"cyclomatic":48,"sloc":{"logical":316,"physical":459},"halstead":{"operators":{"distinct":20,"total":1179,"identifiers":["__stripped__"]},"operands":{"distinct":293,"total":1406,"identifiers":["__stripped__"]},"length":2585,"vocabulary":313,"difficulty":47.98634812286689,"volume":21429.69871932082,"effort":1028332.9829134836,"bugs":7.143232906440273,"time":57129.610161860204}}},"functions":[{"name":"<anonymous>","sloc":{"logical":63,"physical":436},"cyclomatic":8,"halstead":{"operators":{"distinct":15,"total":227,"identifiers":["__stripped__"]},"operands":{"distinct":118,"total":292,"identifiers":["__stripped__"]},"length":519,"vocabulary":133,"difficulty":18.559322033898304,"volume":3661.6915840251177,"effort":67958.51329673735,"bugs":1.2205638613417058,"time":3775.472960929853},"params":24,"line":10,"cyclomaticDensity":12.698412698412698,"complexity":{"cyclomatic":8,"sloc":{"logical":63,"physical":436},"halstead":{"operators":{"distinct":15,"total":227,"identifiers":["__stripped__"]},"operands":{"distinct":118,"total":292,"identifiers":["__stripped__"]},"length":519,"vocabulary":133,"difficulty":18.559322033898304,"volume":3661.6915840251177,"effort":67958.51329673735,"bugs":1.2205638613417058,"time":3775.472960929853}}},{"name":"$scope.index","sloc":{"logical":3,"physical":6},"cyclomatic":1,"halstead":{"operators":{"distinct":2,"total":6,"identifiers":["__stripped__"]},"operands":{"distinct":4,"total":6,"identifiers":["__stripped__"]},"length":12,"vocabulary":6,"difficulty":1.5,"volume":31.019550008653873,"effort":46.529325012980806,"bugs":0.010339850002884624,"time":2.584962500721156},"params":0,"line":40,"cyclomaticDensity":33.33333333333333,"complexity":{"cyclomatic":1,"sloc":{"logical":3,"physical":6},"halstead":{"operators":{"distinct":2,"total":6,"identifiers":["__stripped__"]},"operands":{"distinct":4,"total":6,"identifiers":["__stripped__"]},"length":12,"vocabulary":6,"difficulty":1.5,"volume":31.019550008653873,"effort":46.529325012980806,"bugs":0.010339850002884624,"time":2.584962500721156}}},{"name":"$scope.getCountries","sloc":{"logical":3,"physical":7},"cyclomatic":1,"halstead":{"operators":{"distinct":6,"total":8,"identifiers":["__stripped__"]},"operands":{"distinct":6,"total":9,"identifiers":["__stripped__"]},"length":17,"vocabulary":12,"difficulty":4.5,"volume":60.94436251225966,"effort":274.24963130516846,"bugs":0.020314787504086555,"time":15.236090628064915},"params":0,"line":71,"cyclomaticDensity":33.33333333333333,"complexity":{"cyclomatic":1,"sloc":{"logical":3,"physical":7},"halstead":{"operators":{"distinct":6,"total":8,"identifiers":["__stripped__"]},"operands":{"distinct":6,"total":9,"identifiers":["__stripped__"]},"length":17,"vocabulary":12,"difficulty":4.5,"volume":60.94436251225966,"effort":274.24963130516846,"bugs":0.020314787504086555,"time":15.236090628064915}}},{"name":"<anonymous>","sloc":{"logical":1,"physical":3},"cyclomatic":1,"halstead":{"operators":{"distinct":2,"total":3,"identifiers":["__stripped__"]},"operands":{"distinct":4,"total":5,"identifiers":["__stripped__"]},"length":8,"vocabulary":6,"difficulty":1.25,"volume":20.67970000576925,"effort":25.84962500721156,"bugs":0.006893233335256416,"time":1.43609027817842},"params":1,"line":74,"cyclomaticDensity":100,"complexity":{"cyclomatic":1,"sloc":{"logical":1,"physical":3},"halstead":{"operators":{"distinct":2,"total":3,"identifiers":["__stripped__"]},"operands":{"distinct":4,"total":5,"identifiers":["__stripped__"]},"length":8,"vocabulary":6,"difficulty":1.25,"volume":20.67970000576925,"effort":25.84962500721156,"bugs":0.006893233335256416,"time":1.43609027817842}}},{"name":"$scope.get_providers","sloc":{"logical":1,"physical":15},"cyclomatic":1,"halstead":{"operators":{"distinct":3,"total":3,"identifiers":["__stripped__"]},"operands":{"distinct":3,"total":3,"identifiers":["__stripped__"]},"length":6,"vocabulary":6,"difficulty":1.5,"volume":15.509775004326936,"effort":23.264662506490403,"bugs":0.005169925001442312,"time":1.292481250360578},"params":0,"line":78,"cyclomaticDensity":100,"complexity":{"cyclomatic":1,"sloc":{"logical":1,"physical":15},"halstead":{"operators":{"distinct":3,"total":3,"identifiers":["__stripped__"]},"operands":{"distinct":3,"total":3,"identifiers":["__stripped__"]},"length":6,"vocabulary":6,"difficulty":1.5,"volume":15.509775004326936,"effort":23.264662506490403,"bugs":0.005169925001442312,"time":1.292481250360578}}},{"name":"<anonymous>","sloc":{"logical":1,"physical":13},"cyclomatic":1,"halstead":{"operators":{"distinct":3,"total":4,"identifiers":["__stripped__"]},"operands":{"distinct":5,"total":6,"identifiers":["__stripped__"]},"length":10,"vocabulary":8,"difficulty":1.7999999999999998,"volume":30,"effort":53.99999999999999,"bugs":0.01,"time":2.9999999999999996},"params":1,"line":79,"cyclomaticDensity":100,"complexity":{"cyclomatic":1,"sloc":{"logical":1,"physical":13},"halstead":{"operators":{"distinct":3,"total":4,"identifiers":["__stripped__"]},"operands":{"distinct":5,"total":6,"identifiers":["__stripped__"]},"length":10,"vocabulary":8,"difficulty":1.7999999999999998,"volume":30,"effort":53.99999999999999,"bugs":0.01,"time":2.9999999999999996}}},{"name":"<anonymous>","sloc":{"logical":6,"physical":11},"cyclomatic":4,"halstead":{"operators":{"distinct":4,"total":18,"identifiers":["__stripped__"]},"operands":{"distinct":10,"total":22,"identifiers":["__stripped__"]},"length":40,"vocabulary":14,"difficulty":4.4,"volume":152.29419688230416,"effort":670.0944662821383,"bugs":0.05076473229410139,"time":37.22747034900769},"params":1,"line":80,"cyclomaticDensity":66.66666666666666,"complexity":{"cyclomatic":4,"sloc":{"logical":6,"physical":11},"halstead":{"operators":{"distinct":4,"total":18,"identifiers":["__stripped__"]},"operands":{"distinct":10,"total":22,"identifiers":["__stripped__"]},"length":40,"vocabulary":14,"difficulty":4.4,"volume":152.29419688230416,"effort":670.0944662821383,"bugs":0.05076473229410139,"time":37.22747034900769}}},{"name":"<anonymous>","sloc":{"logical":31,"physical":37},"cyclomatic":8,"halstead":{"operators":{"distinct":14,"total":121,"identifiers":["__stripped__"]},"operands":{"distinct":46,"total":140,"identifiers":["__stripped__"]},"length":261,"vocabulary":60,"difficulty":21.304347826086957,"volume":1541.6984454538233,"effort":32844.879924885805,"bugs":0.5138994818179411,"time":1824.7155513825446},"params":2,"line":93,"cyclomaticDensity":25.806451612903224,"complexity":{"cyclomatic":8,"sloc":{"logical":31,"physical":37},"halstead":{"operators":{"distinct":14,"total":121,"identifiers":["__stripped__"]},"operands":{"distinct":46,"total":140,"identifiers":["__stripped__"]},"length":261,"vocabulary":60,"difficulty":21.304347826086957,"volume":1541.6984454538233,"effort":32844.879924885805,"bugs":0.5138994818179411,"time":1824.7155513825446}}},{"name":"<anonymous>","sloc":{"logical":5,"physical":31},"cyclomatic":1,"halstead":{"operators":{"distinct":6,"total":17,"identifiers":["__stripped__"]},"operands":{"distinct":16,"total":21,"identifiers":["__stripped__"]},"length":38,"vocabulary":22,"difficulty":3.9375,"volume":169.4584015082173,"effort":667.2424559386056,"bugs":0.05648613383607243,"time":37.06902532992254},"params":2,"line":142,"cyclomaticDensity":20,"complexity":{"cyclomatic":1,"sloc":{"logical":5,"physical":31},"halstead":{"operators":{"distinct":6,"total":17,"identifiers":["__stripped__"]},"operands":{"distinct":16,"total":21,"identifiers":["__stripped__"]},"length":38,"vocabulary":22,"difficulty":3.9375,"volume":169.4584015082173,"effort":667.2424559386056,"bugs":0.05648613383607243,"time":37.06902532992254}}},{"name":"<anonymous>","sloc":{"logical":14,"physical":24},"cyclomatic":2,"halstead":{"operators":{"distinct":10,"total":36,"identifiers":["__stripped__"]},"operands":{"distinct":26,"total":47,"identifiers":["__stripped__"]},"length":83,"vocabulary":36,"difficulty":9.038461538461538,"volume":429.1037751197119,"effort":3878.437967428165,"bugs":0.14303459170657062,"time":215.4687759682314},"params":1,"line":148,"cyclomaticDensity":14.285714285714285,"complexity":{"cyclomatic":2,"sloc":{"logical":14,"physical":24},"halstead":{"operators":{"distinct":10,"total":36,"identifiers":["__stripped__"]},"operands":{"distinct":26,"total":47,"identifiers":["__stripped__"]},"length":83,"vocabulary":36,"difficulty":9.038461538461538,"volume":429.1037751197119,"effort":3878.437967428165,"bugs":0.14303459170657062,"time":215.4687759682314}}},{"name":"<anonymous>","sloc":{"logical":1,"physical":3},"cyclomatic":1,"halstead":{"operators":{"distinct":2,"total":3,"identifiers":["__stripped__"]},"operands":{"distinct":3,"total":3,"identifiers":["__stripped__"]},"length":6,"vocabulary":5,"difficulty":1,"volume":13.931568569324174,"effort":13.931568569324174,"bugs":0.004643856189774725,"time":0.7739760316291208},"params":0,"line":154,"cyclomaticDensity":100,"complexity":{"cyclomatic":1,"sloc":{"logical":1,"physical":3},"halstead":{"operators":{"distinct":2,"total":3,"identifiers":["__stripped__"]},"operands":{"distinct":3,"total":3,"identifiers":["__stripped__"]},"length":6,"vocabulary":5,"difficulty":1,"volume":13.931568569324174,"effort":13.931568569324174,"bugs":0.004643856189774725,"time":0.7739760316291208}}},{"name":"$scope.openLoginModal","sloc":{"logical":40,"physical":58},"cyclomatic":7,"halstead":{"operators":{"distinct":14,"total":99,"identifiers":["__stripped__"]},"operands":{"distinct":59,"total":124,"identifiers":["__stripped__"]},"length":223,"vocabulary":73,"difficulty":14.711864406779663,"volume":1380.330876630244,"effort":20307.240693475454,"bugs":0.4601102922100813,"time":1128.1800385264141},"params":3,"line":173,"cyclomaticDensity":17.5,"complexity":{"cyclomatic":7,"sloc":{"logical":40,"physical":58},"halstead":{"operators":{"distinct":14,"total":99,"identifiers":["__stripped__"]},"operands":{"distinct":59,"total":124,"identifiers":["__stripped__"]},"length":223,"vocabulary":73,"difficulty":14.711864406779663,"volume":1380.330876630244,"effort":20307.240693475454,"bugs":0.4601102922100813,"time":1128.1800385264141}}},{"name":"tabactive","sloc":{"logical":1,"physical":3},"cyclomatic":1,"halstead":{"operators":{"distinct":1,"total":1,"identifiers":["__stripped__"]},"operands":{"distinct":1,"total":1,"identifiers":["__stripped__"]},"length":2,"vocabulary":2,"difficulty":0.5,"volume":2,"effort":1,"bugs":0.0006666666666666666,"time":0.05555555555555555},"params":0,"line":222,"cyclomaticDensity":100,"complexity":{"cyclomatic":1,"sloc":{"logical":1,"physical":3},"halstead":{"operators":{"distinct":1,"total":1,"identifiers":["__stripped__"]},"operands":{"distinct":1,"total":1,"identifiers":["__stripped__"]},"length":2,"vocabulary":2,"difficulty":0.5,"volume":2,"effort":1,"bugs":0.0006666666666666666,"time":0.05555555555555555}}},{"name":"$scope.openQuoteRequestModal","sloc":{"logical":12,"physical":26},"cyclomatic":1,"halstead":{"operators":{"distinct":6,"total":22,"identifiers":["__stripped__"]},"operands":{"distinct":21,"total":32,"identifiers":["__stripped__"]},"length":54,"vocabulary":27,"difficulty":4.571428571428571,"volume":256.76392511682735,"effort":1173.7779433912108,"bugs":0.08558797503894246,"time":65.20988574395615},"params":5,"line":231,"cyclomaticDensity":8.333333333333332,"complexity":{"cyclomatic":1,"sloc":{"logical":12,"physical":26},"halstead":{"operators":{"distinct":6,"total":22,"identifiers":["__stripped__"]},"operands":{"distinct":21,"total":32,"identifiers":["__stripped__"]},"length":54,"vocabulary":27,"difficulty":4.571428571428571,"volume":256.76392511682735,"effort":1173.7779433912108,"bugs":0.08558797503894246,"time":65.20988574395615}}},{"name":"Category_id","sloc":{"logical":1,"physical":3},"cyclomatic":1,"halstead":{"operators":{"distinct":1,"total":1,"identifiers":["__stripped__"]},"operands":{"distinct":1,"total":1,"identifiers":["__stripped__"]},"length":2,"vocabulary":2,"difficulty":0.5,"volume":2,"effort":1,"bugs":0.0006666666666666666,"time":0.05555555555555555},"params":0,"line":239,"cyclomaticDensity":100,"complexity":{"cyclomatic":1,"sloc":{"logical":1,"physical":3},"halstead":{"operators":{"distinct":1,"total":1,"identifiers":["__stripped__"]},"operands":{"distinct":1,"total":1,"identifiers":["__stripped__"]},"length":2,"vocabulary":2,"difficulty":0.5,"volume":2,"effort":1,"bugs":0.0006666666666666666,"time":0.05555555555555555}}},{"name":"Service_id","sloc":{"logical":1,"physical":3},"cyclomatic":1,"halstead":{"operators":{"distinct":1,"total":1,"identifiers":["__stripped__"]},"operands":{"distinct":1,"total":1,"identifiers":["__stripped__"]},"length":2,"vocabulary":2,"difficulty":0.5,"volume":2,"effort":1,"bugs":0.0006666666666666666,"time":0.05555555555555555},"params":0,"line":242,"cyclomaticDensity":100,"complexity":{"cyclomatic":1,"sloc":{"logical":1,"physical":3},"halstead":{"operators":{"distinct":1,"total":1,"identifiers":["__stripped__"]},"operands":{"distinct":1,"total":1,"identifiers":["__stripped__"]},"length":2,"vocabulary":2,"difficulty":0.5,"volume":2,"effort":1,"bugs":0.0006666666666666666,"time":0.05555555555555555}}},{"name":"type","sloc":{"logical":1,"physical":3},"cyclomatic":1,"halstead":{"operators":{"distinct":1,"total":1,"identifiers":["__stripped__"]},"operands":{"distinct":1,"total":1,"identifiers":["__stripped__"]},"length":2,"vocabulary":2,"difficulty":0.5,"volume":2,"effort":1,"bugs":0.0006666666666666666,"time":0.05555555555555555},"params":0,"line":245,"cyclomaticDensity":100,"complexity":{"cyclomatic":1,"sloc":{"logical":1,"physical":3},"halstead":{"operators":{"distinct":1,"total":1,"identifiers":["__stripped__"]},"operands":{"distinct":1,"total":1,"identifiers":["__stripped__"]},"length":2,"vocabulary":2,"difficulty":0.5,"volume":2,"effort":1,"bugs":0.0006666666666666666,"time":0.05555555555555555}}},{"name":"title","sloc":{"logical":1,"physical":3},"cyclomatic":1,"halstead":{"operators":{"distinct":1,"total":1,"identifiers":["__stripped__"]},"operands":{"distinct":1,"total":1,"identifiers":["__stripped__"]},"length":2,"vocabulary":2,"difficulty":0.5,"volume":2,"effort":1,"bugs":0.0006666666666666666,"time":0.05555555555555555},"params":0,"line":248,"cyclomaticDensity":100,"complexity":{"cyclomatic":1,"sloc":{"logical":1,"physical":3},"halstead":{"operators":{"distinct":1,"total":1,"identifiers":["__stripped__"]},"operands":{"distinct":1,"total":1,"identifiers":["__stripped__"]},"length":2,"vocabulary":2,"difficulty":0.5,"volume":2,"effort":1,"bugs":0.0006666666666666666,"time":0.05555555555555555}}},{"name":"service_type","sloc":{"logical":1,"physical":3},"cyclomatic":1,"halstead":{"operators":{"distinct":1,"total":1,"identifiers":["__stripped__"]},"operands":{"distinct":1,"total":1,"identifiers":["__stripped__"]},"length":2,"vocabulary":2,"difficulty":0.5,"volume":2,"effort":1,"bugs":0.0006666666666666666,"time":0.05555555555555555},"params":0,"line":251,"cyclomaticDensity":100,"complexity":{"cyclomatic":1,"sloc":{"logical":1,"physical":3},"halstead":{"operators":{"distinct":1,"total":1,"identifiers":["__stripped__"]},"operands":{"distinct":1,"total":1,"identifiers":["__stripped__"]},"length":2,"vocabulary":2,"difficulty":0.5,"volume":2,"effort":1,"bugs":0.0006666666666666666,"time":0.05555555555555555}}},{"name":"$scope.cancel","sloc":{"logical":22,"physical":31},"cyclomatic":5,"halstead":{"operators":{"distinct":11,"total":66,"identifiers":["__stripped__"]},"operands":{"distinct":33,"total":72,"identifiers":["__stripped__"]},"length":138,"vocabulary":44,"difficulty":12,"volume":753.4015633719471,"effort":9040.818760463364,"bugs":0.2511338544573157,"time":502.2677089146313},"params":0,"line":257,"cyclomaticDensity":22.727272727272727,"complexity":{"cyclomatic":5,"sloc":{"logical":22,"physical":31},"halstead":{"operators":{"distinct":11,"total":66,"identifiers":["__stripped__"]},"operands":{"distinct":33,"total":72,"identifiers":["__stripped__"]},"length":138,"vocabulary":44,"difficulty":12,"volume":753.4015633719471,"effort":9040.818760463364,"bugs":0.2511338544573157,"time":502.2677089146313}}},{"name":"<anonymous>","sloc":{"logical":2,"physical":4},"cyclomatic":1,"halstead":{"operators":{"distinct":2,"total":5,"identifiers":["__stripped__"]},"operands":{"distinct":8,"total":8,"identifiers":["__stripped__"]},"length":13,"vocabulary":10,"difficulty":1,"volume":43.18506523353572,"effort":43.18506523353572,"bugs":0.014395021744511906,"time":2.399170290751984},"params":0,"line":276,"cyclomaticDensity":50,"complexity":{"cyclomatic":1,"sloc":{"logical":2,"physical":4},"halstead":{"operators":{"distinct":2,"total":5,"identifiers":["__stripped__"]},"operands":{"distinct":8,"total":8,"identifiers":["__stripped__"]},"length":13,"vocabulary":10,"difficulty":1,"volume":43.18506523353572,"effort":43.18506523353572,"bugs":0.014395021744511906,"time":2.399170290751984}}},{"name":"$scope.switch_tab","sloc":{"logical":10,"physical":17},"cyclomatic":2,"halstead":{"operators":{"distinct":9,"total":31,"identifiers":["__stripped__"]},"operands":{"distinct":20,"total":39,"identifiers":["__stripped__"]},"length":70,"vocabulary":29,"difficulty":8.775,"volume":340.0586696589301,"effort":2984.014826257112,"bugs":0.11335288988631004,"time":165.77860145872845},"params":1,"line":288,"cyclomaticDensity":20,"complexity":{"cyclomatic":2,"sloc":{"logical":10,"physical":17},"halstead":{"operators":{"distinct":9,"total":31,"identifiers":["__stripped__"]},"operands":{"distinct":20,"total":39,"identifiers":["__stripped__"]},"length":70,"vocabulary":29,"difficulty":8.775,"volume":340.0586696589301,"effort":2984.014826257112,"bugs":0.11335288988631004,"time":165.77860145872845}}},{"name":"$scope.homePageScroll","sloc":{"logical":6,"physical":9},"cyclomatic":2,"halstead":{"operators":{"distinct":7,"total":13,"identifiers":["__stripped__"]},"operands":{"distinct":13,"total":16,"identifiers":["__stripped__"]},"length":29,"vocabulary":20,"difficulty":4.307692307692308,"volume":125.33591475173351,"effort":539.9085558536214,"bugs":0.041778638250577836,"time":29.99491976964563},"params":1,"line":305,"cyclomaticDensity":33.33333333333333,"complexity":{"cyclomatic":2,"sloc":{"logical":6,"physical":9},"halstead":{"operators":{"distinct":7,"total":13,"identifiers":["__stripped__"]},"operands":{"distinct":13,"total":16,"identifiers":["__stripped__"]},"length":29,"vocabulary":20,"difficulty":4.307692307692308,"volume":125.33591475173351,"effort":539.9085558536214,"bugs":0.041778638250577836,"time":29.99491976964563}}},{"name":"$scope.saveHomeContact","sloc":{"logical":1,"physical":11},"cyclomatic":1,"halstead":{"operators":{"distinct":3,"total":4,"identifiers":["__stripped__"]},"operands":{"distinct":5,"total":5,"identifiers":["__stripped__"]},"length":9,"vocabulary":8,"difficulty":1.5,"volume":27,"effort":40.5,"bugs":0.009,"time":2.25},"params":0,"line":314,"cyclomaticDensity":100,"complexity":{"cyclomatic":1,"sloc":{"logical":1,"physical":11},"halstead":{"operators":{"distinct":3,"total":4,"identifiers":["__stripped__"]},"operands":{"distinct":5,"total":5,"identifiers":["__stripped__"]},"length":9,"vocabulary":8,"difficulty":1.5,"volume":27,"effort":40.5,"bugs":0.009,"time":2.25}}},{"name":"<anonymous>","sloc":{"logical":6,"physical":9},"cyclomatic":2,"halstead":{"operators":{"distinct":7,"total":19,"identifiers":["__stripped__"]},"operands":{"distinct":16,"total":26,"identifiers":["__stripped__"]},"length":45,"vocabulary":23,"difficulty":5.6875,"volume":203.5602880225656,"effort":1157.7491381283419,"bugs":0.0678534293408552,"time":64.31939656268565},"params":1,"line":315,"cyclomaticDensity":33.33333333333333,"complexity":{"cyclomatic":2,"sloc":{"logical":6,"physical":9},"halstead":{"operators":{"distinct":7,"total":19,"identifiers":["__stripped__"]},"operands":{"distinct":16,"total":26,"identifiers":["__stripped__"]},"length":45,"vocabulary":23,"difficulty":5.6875,"volume":203.5602880225656,"effort":1157.7491381283419,"bugs":0.0678534293408552,"time":64.31939656268565}}},{"name":"$scope.getMyuser","sloc":{"logical":2,"physical":11},"cyclomatic":2,"halstead":{"operators":{"distinct":4,"total":5,"identifiers":["__stripped__"]},"operands":{"distinct":5,"total":5,"identifiers":["__stripped__"]},"length":10,"vocabulary":9,"difficulty":2,"volume":31.699250014423125,"effort":63.39850002884625,"bugs":0.010566416671474375,"time":3.5221388904914583},"params":0,"line":325,"cyclomaticDensity":100,"complexity":{"cyclomatic":2,"sloc":{"logical":2,"physical":11},"halstead":{"operators":{"distinct":4,"total":5,"identifiers":["__stripped__"]},"operands":{"distinct":5,"total":5,"identifiers":["__stripped__"]},"length":10,"vocabulary":9,"difficulty":2,"volume":31.699250014423125,"effort":63.39850002884625,"bugs":0.010566416671474375,"time":3.5221388904914583}}},{"name":"<anonymous>","sloc":{"logical":2,"physical":7},"cyclomatic":1,"halstead":{"operators":{"distinct":4,"total":5,"identifiers":["__stripped__"]},"operands":{"distinct":7,"total":8,"identifiers":["__stripped__"]},"length":13,"vocabulary":11,"difficulty":2.2857142857142856,"volume":44.97261104228487,"effort":102.79453952522255,"bugs":0.01499087034742829,"time":5.710807751401252},"params":1,"line":327,"cyclomaticDensity":50,"complexity":{"cyclomatic":1,"sloc":{"logical":2,"physical":7},"halstead":{"operators":{"distinct":4,"total":5,"identifiers":["__stripped__"]},"operands":{"distinct":7,"total":8,"identifiers":["__stripped__"]},"length":13,"vocabulary":11,"difficulty":2.2857142857142856,"volume":44.97261104228487,"effort":102.79453952522255,"bugs":0.01499087034742829,"time":5.710807751401252}}},{"name":"<anonymous>","sloc":{"logical":1,"physical":4},"cyclomatic":1,"halstead":{"operators":{"distinct":4,"total":7,"identifiers":["__stripped__"]},"operands":{"distinct":5,"total":8,"identifiers":["__stripped__"]},"length":15,"vocabulary":9,"difficulty":3.2,"volume":47.548875021634686,"effort":152.156400069231,"bugs":0.01584962500721156,"time":8.453133337179501},"params":0,"line":329,"cyclomaticDensity":100,"complexity":{"cyclomatic":1,"sloc":{"logical":1,"physical":4},"halstead":{"operators":{"distinct":4,"total":7,"identifiers":["__stripped__"]},"operands":{"distinct":5,"total":8,"identifiers":["__stripped__"]},"length":15,"vocabulary":9,"difficulty":3.2,"volume":47.548875021634686,"effort":152.156400069231,"bugs":0.01584962500721156,"time":8.453133337179501}}},{"name":"$scope.navigate_dashbooard","sloc":{"logical":4,"physical":6},"cyclomatic":1,"halstead":{"operators":{"distinct":4,"total":12,"identifiers":["__stripped__"]},"operands":{"distinct":12,"total":16,"identifiers":["__stripped__"]},"length":28,"vocabulary":16,"difficulty":2.6666666666666665,"volume":112,"effort":298.66666666666663,"bugs":0.037333333333333336,"time":16.59259259259259},"params":0,"line":336,"cyclomaticDensity":25,"complexity":{"cyclomatic":1,"sloc":{"logical":4,"physical":6},"halstead":{"operators":{"distinct":4,"total":12,"identifiers":["__stripped__"]},"operands":{"distinct":12,"total":16,"identifiers":["__stripped__"]},"length":28,"vocabulary":16,"difficulty":2.6666666666666665,"volume":112,"effort":298.66666666666663,"bugs":0.037333333333333336,"time":16.59259259259259}}},{"name":"$scope.onlydashbord","sloc":{"logical":9,"physical":13},"cyclomatic":3,"halstead":{"operators":{"distinct":7,"total":15,"identifiers":["__stripped__"]},"operands":{"distinct":12,"total":21,"identifiers":["__stripped__"]},"length":36,"vocabulary":19,"difficulty":6.125,"volume":152.92539048396907,"effort":936.6680167143105,"bugs":0.050975130161323025,"time":52.03711203968392},"params":1,"line":342,"cyclomaticDensity":33.33333333333333,"complexity":{"cyclomatic":3,"sloc":{"logical":9,"physical":13},"halstead":{"operators":{"distinct":7,"total":15,"identifiers":["__stripped__"]},"operands":{"distinct":12,"total":21,"identifiers":["__stripped__"]},"length":36,"vocabulary":19,"difficulty":6.125,"volume":152.92539048396907,"effort":936.6680167143105,"bugs":0.050975130161323025,"time":52.03711203968392}}},{"name":"$scope.switch_portal","sloc":{"logical":43,"physical":80},"cyclomatic":12,"halstead":{"operators":{"distinct":15,"total":378,"identifiers":["__stripped__"]},"operands":{"distinct":46,"total":379,"identifiers":["__stripped__"]},"length":757,"vocabulary":61,"difficulty":61.79347826086957,"volume":4489.568164535105,"effort":277426.0327758921,"bugs":1.4965227215117016,"time":15412.557376438452},"params":1,"line":355,"cyclomaticDensity":27.906976744186046,"complexity":{"cyclomatic":12,"sloc":{"logical":43,"physical":80},"halstead":{"operators":{"distinct":15,"total":378,"identifiers":["__stripped__"]},"operands":{"distinct":46,"total":379,"identifiers":["__stripped__"]},"length":757,"vocabulary":61,"difficulty":61.79347826086957,"volume":4489.568164535105,"effort":277426.0327758921,"bugs":1.4965227215117016,"time":15412.557376438452}}},{"name":"<anonymous>","sloc":{"logical":3,"physical":6},"cyclomatic":1,"halstead":{"operators":{"distinct":4,"total":5,"identifiers":["__stripped__"]},"operands":{"distinct":7,"total":8,"identifiers":["__stripped__"]},"length":13,"vocabulary":11,"difficulty":2.2857142857142856,"volume":44.97261104228487,"effort":102.79453952522255,"bugs":0.01499087034742829,"time":5.710807751401252},"params":0,"line":364,"cyclomaticDensity":33.33333333333333,"complexity":{"cyclomatic":1,"sloc":{"logical":3,"physical":6},"halstead":{"operators":{"distinct":4,"total":5,"identifiers":["__stripped__"]},"operands":{"distinct":7,"total":8,"identifiers":["__stripped__"]},"length":13,"vocabulary":11,"difficulty":2.2857142857142856,"volume":44.97261104228487,"effort":102.79453952522255,"bugs":0.01499087034742829,"time":5.710807751401252}}},{"name":"<anonymous>","sloc":{"logical":3,"physical":6},"cyclomatic":1,"halstead":{"operators":{"distinct":4,"total":5,"identifiers":["__stripped__"]},"operands":{"distinct":7,"total":8,"identifiers":["__stripped__"]},"length":13,"vocabulary":11,"difficulty":2.2857142857142856,"volume":44.97261104228487,"effort":102.79453952522255,"bugs":0.01499087034742829,"time":5.710807751401252},"params":0,"line":404,"cyclomaticDensity":33.33333333333333,"complexity":{"cyclomatic":1,"sloc":{"logical":3,"physical":6},"halstead":{"operators":{"distinct":4,"total":5,"identifiers":["__stripped__"]},"operands":{"distinct":7,"total":8,"identifiers":["__stripped__"]},"length":13,"vocabulary":11,"difficulty":2.2857142857142856,"volume":44.97261104228487,"effort":102.79453952522255,"bugs":0.01499087034742829,"time":5.710807751401252}}},{"name":"$scope.openSearch","sloc":{"logical":4,"physical":7},"cyclomatic":2,"halstead":{"operators":{"distinct":5,"total":8,"identifiers":["__stripped__"]},"operands":{"distinct":4,"total":9,"identifiers":["__stripped__"]},"length":17,"vocabulary":9,"difficulty":5.625,"volume":53.88872502451932,"effort":303.12407826292116,"bugs":0.017962908341506437,"time":16.840226570162287},"params":0,"line":436,"cyclomaticDensity":50,"complexity":{"cyclomatic":2,"sloc":{"logical":4,"physical":7},"halstead":{"operators":{"distinct":5,"total":8,"identifiers":["__stripped__"]},"operands":{"distinct":4,"total":9,"identifiers":["__stripped__"]},"length":17,"vocabulary":9,"difficulty":5.625,"volume":53.88872502451932,"effort":303.12407826292116,"bugs":0.017962908341506437,"time":16.840226570162287}}},{"name":"<anonymous>","sloc":{"logical":6,"physical":13},"cyclomatic":2,"halstead":{"operators":{"distinct":7,"total":13,"identifiers":["__stripped__"]},"operands":{"distinct":12,"total":19,"identifiers":["__stripped__"]},"length":32,"vocabulary":19,"difficulty":5.541666666666666,"volume":135.93368043019473,"effort":753.299145717329,"bugs":0.04531122681006491,"time":41.849952539851614},"params":4,"line":447,"cyclomaticDensity":33.33333333333333,"complexity":{"cyclomatic":2,"sloc":{"logical":6,"physical":13},"halstead":{"operators":{"distinct":7,"total":13,"identifiers":["__stripped__"]},"operands":{"distinct":12,"total":19,"identifiers":["__stripped__"]},"length":32,"vocabulary":19,"difficulty":5.541666666666666,"volume":135.93368043019473,"effort":753.299145717329,"bugs":0.04531122681006491,"time":41.849952539851614}}},{"name":"$scope.ok","sloc":{"logical":1,"physical":3},"cyclomatic":1,"halstead":{"operators":{"distinct":2,"total":2,"identifiers":["__stripped__"]},"operands":{"distinct":2,"total":2,"identifiers":["__stripped__"]},"length":4,"vocabulary":4,"difficulty":1,"volume":8,"effort":8,"bugs":0.0026666666666666666,"time":0.4444444444444444},"params":0,"line":453,"cyclomaticDensity":100,"complexity":{"cyclomatic":1,"sloc":{"logical":1,"physical":3},"halstead":{"operators":{"distinct":2,"total":2,"identifiers":["__stripped__"]},"operands":{"distinct":2,"total":2,"identifiers":["__stripped__"]},"length":4,"vocabulary":4,"difficulty":1,"volume":8,"effort":8,"bugs":0.0026666666666666666,"time":0.4444444444444444}}},{"name":"<anonymous>","sloc":{"logical":1,"physical":3},"cyclomatic":1,"halstead":{"operators":{"distinct":2,"total":2,"identifiers":["__stripped__"]},"operands":{"distinct":3,"total":3,"identifiers":["__stripped__"]},"length":5,"vocabulary":5,"difficulty":1,"volume":11.60964047443681,"effort":11.60964047443681,"bugs":0.0038698801581456034,"time":0.6449800263576005},"params":0,"line":456,"cyclomaticDensity":100,"complexity":{"cyclomatic":1,"sloc":{"logical":1,"physical":3},"halstead":{"operators":{"distinct":2,"total":2,"identifiers":["__stripped__"]},"operands":{"distinct":3,"total":3,"identifiers":["__stripped__"]},"length":5,"vocabulary":5,"difficulty":1,"volume":11.60964047443681,"effort":11.60964047443681,"bugs":0.0038698801581456034,"time":0.6449800263576005}}}],"dependencies":[],"maintainability":60.976962791125736,"params":1.3513513513513513,"module":"controllers/main.js"},"jshint":{"messages":[{"severity":"error","line":1,"column":1,"message":"Use the function form of \"use strict\".","source":"Use the function form of \"use strict\"."},{"severity":"error","line":9,"column":1,"message":"'angular' is not defined.","source":"'{a}' is not defined."},{"severity":"error","line":15,"column":27,"message":"'window' is not defined.","source":"'{a}' is not defined."},{"severity":"error","line":15,"column":61,"message":"'window' is not defined.","source":"'{a}' is not defined."},{"severity":"error","line":49,"column":17,"message":"'angular' is not defined.","source":"'{a}' is not defined."},{"severity":"error","line":80,"column":17,"message":"'angular' is not defined.","source":"'{a}' is not defined."},{"severity":"error","line":109,"column":25,"message":"'angular' is not defined.","source":"'{a}' is not defined."},{"severity":"error","line":149,"column":21,"message":"'angular' is not defined.","source":"'{a}' is not defined."},{"severity":"error","line":169,"column":21,"message":"'window' is not defined.","source":"'{a}' is not defined."},{"severity":"error","line":339,"column":13,"message":"'window' is not defined.","source":"'{a}' is not defined."},{"severity":"error","line":446,"column":1,"message":"'angular' is not defined.","source":"'{a}' is not defined."}]}}